requests_apitest_tool/__init__.py
requests_apitest_tool-0.0.1.dist-info/METADATA
requests_apitest_tool-0.0.1.dist-info/WHEEL
requests_apitest_tool-0.0.1.dist-info/entry_points.txt
requests_apitest_tool-0.0.1.dist-info/top_level.txt
requests_apitest_tool-0.0.1.dist-info/RECORD
